parsers/__init__.py
parsers/meituri.py
photo_dl/__init__.py
photo_dl/__main__.py
photo_dl/config.py
photo_dl/download.py
photo_dl/log.py
photo_dl/parse.py
photo_dl/photo_dl.py
photo_dl/request.py
photo_dl/save.py
photo_dl/test.py
photo_dl/parsers/__init__.py
photo_dl/parsers/jav_ink.py
photo_dl/parsers/meituri.py
photo_dl/util/__init__.py
photo_dl/util/config.py
photo_dl/util/request.py
photo_dl/util/save.py
photo_dl-0.0.20.dist-info/LICENSE
photo_dl-0.0.20.dist-info/METADATA
photo_dl-0.0.20.dist-info/WHEEL
photo_dl-0.0.20.dist-info/entry_points.txt
photo_dl-0.0.20.dist-info/top_level.txt
photo_dl-0.0.20.dist-info/RECORD
