Metadata-Version: 2.1
Name: photo-dl
Version: 0.0.20
Summary: A photo album downloader
Home-page: https://github.com/windrises/photo-dl.git
Author: windrises
Author-email: wind_rises@163.com
License: UNKNOWN
Platform: UNKNOWN
Classifier: Programming Language :: Python :: 3
Classifier: License :: OSI Approved :: MIT License
Classifier: Operating System :: OS Independent
Requires-Python: >=3.5
Requires-Dist: requests (>=2.12.0)
Requires-Dist: lxml (>=3.7.0)
